mll/__init__.py
mll1416-0.1.0.dist-info/METADATA
mll1416-0.1.0.dist-info/WHEEL
mll1416-0.1.0.dist-info/top_level.txt
mll1416-0.1.0.dist-info/RECORD
