Metadata-Version: 2.1
Name: mll1416
Version: 0.1.0
Summary: A minimal module named mll for Python utilities
Home-page: https://github.com/yourusername/mll
Author: Peter1416
Author-email: your_email@example.com
License: UNKNOWN
Platform: UNKNOWN
Classifier: Programming Language :: Python :: 3
Classifier: License :: OSI Approved :: MIT License
Classifier: Operating System :: OS Independent
Requires-Python: >=3.6
